bashers/__init__.py
bashers/_bashers_lib
bashers/bashers
bashers/completions/bashers.bash
bashers/github/gh
bashers/project_utils/setup
bashers/project_utils/show
bashers/project_utils/update
bashers-0.4.10.data/scripts/bashers
bashers-0.4.10.dist-info/METADATA
bashers-0.4.10.dist-info/WHEEL
bashers-0.4.10.dist-info/licenses/LICENSE
bashers-0.4.10.dist-info/RECORD
