Metadata-Version: 2.4
Name: bashers
Version: 0.4.10
Summary: Installable bash command helpers
Author: Sung Kim
License: MIT
License-File: LICENSE
Classifier: Development Status :: 3 - Alpha
Classifier: Intended Audience :: Developers
Classifier: License :: OSI Approved :: MIT License
Requires-Python: >=3.8
Provides-Extra: test
Requires-Dist: pytest; extra == 'test'
